matchit/__init__.py
matchit/draw_padel_court.py
matchit/helper_funcs.py
matchit/padel_algorithms.py
matchit/padel_match.py
matchit/padel_player.py
matchit/padel_ranking.py
matchit/assets/logo.svg
matchit-0.2.9.dist-info/licenses/LICENSE
matchit-0.2.9.dist-info/METADATA
matchit-0.2.9.dist-info/WHEEL
matchit-0.2.9.dist-info/top_level.txt
matchit-0.2.9.dist-info/RECORD
