Metadata-Version: 2.4
Name: MatchIt
Version: 0.2.9
Summary: A package for Padel match making and padel player rankings
Author: Andreas Løvgaard
Author-email: Andreas Løvgaard <andreas@loevgaard.dk>
Requires-Python: >=3.13
License-File: LICENSE
Requires-Dist: drawsvg>=2.4.0
Requires-Dist: pandas
Requires-Dist: pydantic
Dynamic: author
Dynamic: license-file
Dynamic: requires-python
